aiovkmusic/__init__.py
aiovkmusic/audio.py
aiovkmusic/audio_url_decoder.py
aiovkmusic/base.py
aiovkmusic/enums.py
aiovkmusic/exceptions.py
aiovkmusic/jconfig.py
aiovkmusic/memory.py
aiovkmusic/model.py
aiovkmusic/music.py
aiovkmusic/session.py
aiovkmusic/utils.py
aiovkmusic/vk_api.py
aiovkmusic-1.6.5.dist-info/LICENSE
aiovkmusic-1.6.5.dist-info/METADATA
aiovkmusic-1.6.5.dist-info/WHEEL
aiovkmusic-1.6.5.dist-info/top_level.txt
aiovkmusic-1.6.5.dist-info/RECORD
