Metadata-Version: 2.1
Name: aiovkmusic
Version: 1.6.5
Summary: Description of aiovkmusic
Home-page: https://github.com/kirilllapushinskiy/aiovkmusic
Author: Kirill Lapushinskiy
Author-email: kirill@lapushinskiy.ru
Project-URL: Bug Tracker, https://github.com/kirilllapushinskiy/aiovkmusic/issues
Classifier: Programming Language :: Python :: 3
Classifier: License :: OSI Approved :: GNU General Public License v3 (GPLv3)
Classifier: Operating System :: OS Independent
Requires-Python: >=3.10
License-File: LICENSE
Requires-Dist: beautifulsoup4 (>=4.11.1)
Requires-Dist: python-ffmpeg (>=1.0.14)
